pyoozie/__init__.py
pyoozie/client.py
pyoozie/exceptions.py
pyoozie/model.py
pyoozie/tags.py
pyoozie/xml.py
pyoozie-0.0.9.dist-info/LICENSE
pyoozie-0.0.9.dist-info/METADATA
pyoozie-0.0.9.dist-info/WHEEL
pyoozie-0.0.9.dist-info/top_level.txt
pyoozie-0.0.9.dist-info/RECORD
